{"blocks":[{"id":"block-1432846254787","dir":"navigation","block":"nav-01-01"},{"id":"block-1427106388876","dir":"headers","block":"header-01-01"},{"id":"block-1424176757693","dir":"content","block":"content-07-02"},{"id":"block-1431372658605","dir":"content","block":"content-05-00"},{"id":"block-1433512978814","dir":"images","block":"images-04-00"},{"id":"block-1433512986466","dir":"images","block":"images-04-00"},{"id":"block-1433513056170","dir":"content","block":"content-02-04"},{"id":"block-1431372710557","dir":"content","block":"content-05-00"},{"id":"block-1431372867887","dir":"forms","block":"form-02-01"},{"id":"block-1424179314195","dir":"footers","block":"footer-02-01"}],"text":[{"path":"section#block-1432846254787 > div:nth-child(1) > div:nth-child(1) > div:nth-child(1) > div:nth-child(1) > div:nth-child(1) > div:nth-child(1) > div:nth-child(1)","html":"<p><a href=\"#\">Home<\/a> <a href=\"#content-10-02-1424176757693\">Services<\/a> <a href=\"#content-08-1431372658605\">Portfolio<\/a> <a href=\"#form-02-01-1431372867887\">Contact<\/a><\/p>\n"},{"path":"section#block-1427106388876 > div:nth-child(1) > div:nth-child(1) > div:nth-child(1) > div:nth-child(1) > div:nth-child(1) > div:nth-child(2) > h1:nth-child(1)","html":"A most excellent landing page builder."},{"path":"section#block-1427106388876 > div:nth-child(1) > div:nth-child(1) > div:nth-child(1) > div:nth-child(1) > div:nth-child(1) > div:nth-child(3) > h3:nth-child(1)","html":"In sit amet justo sed risus eleifend finibus ac nec justo. Praesent posuere a nisi vitae auctor."},{"path":"section#block-1424176757693 > div:nth-child(1) > div:nth-child(1) > div:nth-child(1) > div:nth-child(1) > div:nth-child(1) > div:nth-child(1) > h1:nth-child(1)","html":"Our Services"},{"path":"section#block-1424176757693 > div:nth-child(1) > div:nth-child(1) > div:nth-child(1) > div:nth-child(1) > div:nth-child(1) > div:nth-child(2) > h3:nth-child(1)","html":"Lorem ipsum dolor sit amet, consectetur adipisicing elit, sed do eiusmod tempor incididunt ut et dolore magna aliqua."},{"path":"section#block-1424176757693 > div:nth-child(1) > div:nth-child(1) > div:nth-child(1) > div:nth-child(1) > div:nth-child(2) > div:nth-child(1) > div:nth-child(1) > div:nth-child(2) > div:nth-child(1)","html":"<h4 class=\"margin-md-t-30\">Revenue<\/h4>\n\n<p>Etiam vel consectetur quam, non laoreet urna. Nam lectus diam, venenatis non pretium eu, pharetra ut nulla.<\/p>\n"},{"path":"section#block-1424176757693 > div:nth-child(1) > div:nth-child(1) > div:nth-child(1) > div:nth-child(1) > div:nth-child(2) > div:nth-child(2) > div:nth-child(1) > div:nth-child(2) > div:nth-child(1)","html":"<h4 class=\"margin-md-t-30\">Profit<\/h4>\n\n<p>Etiam vel consectetur quam, non laoreet urna. Nam lectus diam, venenatis non pretium eu, pharetra ut nulla.<\/p>\n"},{"path":"section#block-1424176757693 > div:nth-child(1) > div:nth-child(1) > div:nth-child(1) > div:nth-child(1) > div:nth-child(2) > div:nth-child(3) > div:nth-child(1) > div:nth-child(2) > div:nth-child(1)","html":"<h4 class=\"margin-md-t-30\">Continuity<\/h4>\n\n<p>Etiam vel consectetur quam, non laoreet urna. Nam lectus diam, venenatis non pretium eu, pharetra ut nulla.<\/p>\n"},{"path":"section#block-1431372658605 > div:nth-child(1) > div:nth-child(1) > div:nth-child(1) > div:nth-child(1) > div:nth-child(1) > div:nth-child(1) > div:nth-child(1) > h1:nth-child(1)","html":"Our Portfolio"},{"path":"section#block-1431372658605 > div:nth-child(1) > div:nth-child(1) > div:nth-child(1) > div:nth-child(1) > div:nth-child(1) > div:nth-child(1) > div:nth-child(1) > p:nth-child(2)","html":"Vestibulum ut ultricies libero. Proin vel sapien ut ex vestibulum feugiat ut rhoncus nibh. Nam semper, quam facilisis fringilla porttitor, orci tellus efficitur risus, non auctor sem sapien quis arcu."},{"path":"section#block-1433513056170 > div:nth-child(1) > div:nth-child(1) > div:nth-child(1) > div:nth-child(1) > div:nth-child(1) > div:nth-child(1) > div:nth-child(1)","html":""},{"path":"section#block-1431372710557 > div:nth-child(1) > div:nth-child(1) > div:nth-child(1) > div:nth-child(1) > div:nth-child(1) > div:nth-child(1) > div:nth-child(1) > h1:nth-child(1)","html":"<span style=\"color:#FFFFFF;\">It's all in the title<\/span>\n"},{"path":"section#block-1431372710557 > div:nth-child(1) > div:nth-child(1) > div:nth-child(1) > div:nth-child(1) > div:nth-child(1) > div:nth-child(1) > div:nth-child(1) > p:nth-child(2)","html":"<span style=\"color:#FFFFFF;\">Vestibulum ut ultricies libero. Proin vel sapien ut ex vestibulum feugiat ut rhoncus nibh. Nam semper, quam facilisis fringilla porttitor, orci tellus efficitur risus, non auctor sem sapien quis arcu.<\/span>"},{"path":"section#block-1431372867887 > div:nth-child(1) > div:nth-child(1) > div:nth-child(1) > div:nth-child(1) > div:nth-child(1) > div:nth-child(1) > div:nth-child(1)","html":"<h2>Get in touch<\/h2>\n\n<p>Holisticly predominate extensible testing procedures for reliable supply chains. Dramatically engage top-line web services vis-a-vis cutting-edge deliverables.<\/p>\n"},{"path":"section#block-1431372867887 > div:nth-child(1) > div:nth-child(1) > div:nth-child(1) > div:nth-child(1) > div:nth-child(1) > div:nth-child(2) > div:nth-child(1)","html":"\n                                <h3>Our Headquarters<\/h3>\n                                <p>Sed commodo neque vel sollicitudin dignissim. Morbi in odio consectetur, convallis nisl vel, vestibulum ante. <\/p>\n                            "},{"path":"section#block-1431372867887 > div:nth-child(1) > div:nth-child(1) > div:nth-child(1) > div:nth-child(1) > div:nth-child(1) > div:nth-child(2) > div:nth-child(3)","html":"<h3>Contact us directly<\/h3>\n\n<p>1234 Anything Street<br>\nAnytown, USA 55555<\/p>\n\n<p>+1 (222)555-1212<br>\ninfo@yourcompany.com<\/p>\n"},{"path":"section#block-1424179314195 > div:nth-child(1) > div:nth-child(1) > div:nth-child(1) > div:nth-child(1) > div:nth-child(1) > div:nth-child(2) > div:nth-child(1)","html":"<p>Fusce ut feugiat purus. Duis sit amet rhoncus lacus, cursus lobortis magna. Aliquam justo dolor, lobortis eget efficitur vel, vulputate vel odio.<\/p>\n"},{"path":"section#block-1424179314195 > div:nth-child(1) > div:nth-child(1) > div:nth-child(1) > div:nth-child(1) > div:nth-child(1) > div:nth-child(3) > div:nth-child(1)","html":"<p>\u00a9 Big Business&nbsp;2016. All rights reserved.<\/p>\n"}],"icons":[{"path":"section#block-1424176757693 > div:nth-child(1) > div:nth-child(1) > div:nth-child(1) > div:nth-child(1) > div:nth-child(2) > div:nth-child(1) > div:nth-child(1) > div:nth-child(1) > i:nth-child(1)","color":"rgb(142, 173, 191)","icon":"icon-Coin"},{"path":"section#block-1424176757693 > div:nth-child(1) > div:nth-child(1) > div:nth-child(1) > div:nth-child(1) > div:nth-child(2) > div:nth-child(2) > div:nth-child(1) > div:nth-child(1) > i:nth-child(1)","color":"rgb(142, 173, 191)","icon":"icon-Coins-2"},{"path":"section#block-1424176757693 > div:nth-child(1) > div:nth-child(1) > div:nth-child(1) > div:nth-child(1) > div:nth-child(2) > div:nth-child(3) > div:nth-child(1) > div:nth-child(1) > i:nth-child(1)","color":"rgb(142, 173, 191)","icon":"icon-Coins-3"}],"images":[{"path":"section#block-1427106388876 > div:nth-child(1) > div:nth-child(1) > div:nth-child(1) > div:nth-child(1) > div:nth-child(1) > div:nth-child(1) > img:nth-child(1)","src":"\/stock\/Logos\/logo-big-business.png"},{"path":"section#block-1433512978814 > div:nth-child(1) > div:nth-child(1) > div:nth-child(1) > div:nth-child(1) > div:nth-child(1) > div:nth-child(1) > img:nth-child(1)","src":"\/stock\/Visuals\/small-church.png"},{"path":"section#block-1433512978814 > div:nth-child(1) > div:nth-child(1) > div:nth-child(1) > div:nth-child(1) > div:nth-child(1) > div:nth-child(2) > img:nth-child(1)","src":"\/stock\/Visuals\/small-church.png"},{"path":"section#block-1433512978814 > div:nth-child(1) > div:nth-child(1) > div:nth-child(1) > div:nth-child(1) > div:nth-child(1) > div:nth-child(3) > img:nth-child(1)","src":"\/stock\/Visuals\/small-church.png"},{"path":"section#block-1433512986466 > div:nth-child(1) > div:nth-child(1) > div:nth-child(1) > div:nth-child(1) > div:nth-child(1) > div:nth-child(1) > img:nth-child(1)","src":"\/stock\/Visuals\/small-church.png"},{"path":"section#block-1433512986466 > div:nth-child(1) > div:nth-child(1) > div:nth-child(1) > div:nth-child(1) > div:nth-child(1) > div:nth-child(2) > img:nth-child(1)","src":"\/stock\/Visuals\/small-church.png"},{"path":"section#block-1433512986466 > div:nth-child(1) > div:nth-child(1) > div:nth-child(1) > div:nth-child(1) > div:nth-child(1) > div:nth-child(3) > img:nth-child(1)","src":"\/stock\/Visuals\/small-church.png"},{"path":"section#block-1424179314195 > div:nth-child(1) > div:nth-child(1) > div:nth-child(1) > div:nth-child(1) > div:nth-child(1) > div:nth-child(1) > img:nth-child(1)","src":"\/stock\/Logos\/logo-big-business.png"}],"bg_images":[{"path":"section#block-1427106388876 > div:nth-child(1) > div:nth-child(1)","url":"\/stock\/Backgrounds\/banner-pillars-blurred.png"},{"path":"section#block-1424176757693 > div:nth-child(1)","url":"\/stock\/Visuals\/no-image.png"},{"path":"section#block-1431372710557 > div:nth-child(1)","url":"\/stock\/Backgrounds\/banner-hand-shake.png"},{"path":"section#block-1424179314195 > div:nth-child(1)","url":"\/stock\/Visuals\/no-image.png"}],"color":[{"path":"section#block-1432846254787 > div:nth-child(1) > div:nth-child(1)","rgba":"rgba(0, 0, 0, 0.9)"},{"path":"section#block-1427106388876 > div:nth-child(1) > div:nth-child(1) > div:nth-child(1)","rgba":"transparent"},{"path":"section#block-1424176757693 > div:nth-child(1) > div:nth-child(1)","rgba":"rgb(242, 242, 242)"},{"path":"section#block-1433512978814 > div:nth-child(1) > div:nth-child(1)","rgba":"rgba(255, 255, 255, 0.9)"},{"path":"section#block-1433512986466 > div:nth-child(1) > div:nth-child(1)","rgba":"rgba(255, 255, 255, 0.9)"},{"path":"section#block-1431372710557 > div:nth-child(1) > div:nth-child(1)","rgba":"rgba(120, 120, 120, 0.5)"},{"path":"section#block-1424179314195 > div:nth-child(1) > div:nth-child(1)","rgba":"rgba(0, 0, 0, 0.9)"}],"links":[],"video":[],"forms":[{"path":"section#block-1431372867887 > div:nth-child(1) > div:nth-child(1) > div:nth-child(1) > div:nth-child(1) > div:nth-child(1) > div:nth-child(1) > div:nth-child(2)","html":"\n                                    <textarea data-parsley-id=\"5157\" class=\"mwp-fb-hidden-value\" name=\"form-1427100163196-0-0[]\">Full name<\/textarea><ul id=\"parsley-id-5157\" class=\"parsley-errors-list\"><\/ul>\n<div class=\"form-group form-group-lg mwp-fb-input input-row\" data-mwp-inputtype=\"text\">\n                                        <label for=\"form-1427100163196-0-0\" class=\"mwp-fb-input-label\">Full name<\/label>\n                                        <input data-parsley-id=\"4964\" class=\"form-control mwp-fb-input-field\" id=\"form-1427100163196-0-0\" name=\"form-1427100163196-0-0[]\" required=\"\" type=\"text\"><ul id=\"parsley-id-4964\" class=\"parsley-errors-list\"><\/ul>\n<\/div>\n                                    <textarea data-parsley-id=\"5240\" class=\"mwp-fb-hidden-value\" name=\"email[]\">Email<\/textarea><ul id=\"parsley-id-5240\" class=\"parsley-errors-list\"><\/ul>\n<div class=\"form-group form-group-lg mwp-fb-input input-row\" data-mwp-inputtype=\"email\">\n                                        <label for=\"form-1427100163196-0-1\" class=\"mwp-fb-input-label\">Email<\/label>\n                                        <input data-parsley-id=\"9536\" class=\"form-control mwp-fb-input-field\" id=\"form-1427100163196-0-1\" name=\"email[]\" required=\"\" type=\"email\"><ul id=\"parsley-id-9536\" class=\"parsley-errors-list\"><\/ul>\n<\/div>\n                                    <textarea data-parsley-id=\"4420\" class=\"mwp-fb-hidden-value\" name=\"form-1427100163196-0-2[]\">Phone<\/textarea><ul id=\"parsley-id-4420\" class=\"parsley-errors-list\"><\/ul>\n<div class=\"form-group form-group-lg mwp-fb-input input-row\" data-mwp-inputtype=\"tel\">\n                                        <label for=\"form-1427100163196-0-2\" class=\"mwp-fb-input-label\">Phone<\/label>\n                                        <input data-parsley-id=\"4072\" class=\"form-control mwp-fb-input-field\" id=\"form-1427100163196-0-2\" name=\"form-1427100163196-0-2[]\" required=\"\" type=\"tel\"><ul id=\"parsley-id-4072\" class=\"parsley-errors-list\"><\/ul>\n<\/div>\n                                    <textarea data-parsley-id=\"3700\" class=\"mwp-fb-hidden-value\" name=\"form-1427100163196-0-3[]\">Message<\/textarea><ul id=\"parsley-id-3700\" class=\"parsley-errors-list\"><\/ul>\n<div class=\"form-group form-group-lg mwp-fb-input input-row\" data-mwp-inputtype=\"textArea\">\n                                        <label for=\"form-1427100163196-0-3\" class=\"mwp-fb-input-label\">Message<\/label>\n                                        <textarea data-parsley-id=\"5134\" class=\"form-control mwp-fb-input-field\" rows=\"4\" id=\"form-1427100163196-0-3\" name=\"form-1427100163196-0-3[]\"><\/textarea><ul id=\"parsley-id-5134\" class=\"parsley-errors-list\"><\/ul>\n<\/div>\n                                    <div class=\"form-group form-group-lg mwp-fb-submit\">\n                                        <button type=\"submit\" class=\"btn btn-primary btn-xs-block btn-lg btn-md-inline-block mwp-fb-sendbutton\">Submit<\/button>\n                                    <\/div>\n                                    <textarea class=\"mwp-fb-hidden-value mwp-fb-success-title\">Thank you<\/textarea>\n                                    <textarea class=\"mwp-fb-hidden-value mwp-fb-success-msg\">Thank you for your message. We will get back to you if required.<\/textarea>\n                                    <textarea class=\"mwp-fb-hidden-value mwp-fb-success-btn\">OK<\/textarea>\n                                "}],"iframes":[{"path":"section#block-1431372867887 > div:nth-child(1) > div:nth-child(1) > div:nth-child(1) > div:nth-child(1) > div:nth-child(1) > div:nth-child(2) > iframe:nth-child(2)","src":"\/\/www.openstreetmap.org\/export\/embed.html?bbox=-93.26713174581526%2C44.97919452779862%2C-93.26368510723113%2C44.98292449190208&layer=mapnik&marker=44.981059540182926%2C-93.26540842652321","settings":""}]}